rosmsg_dict_converter/__init__.py
rosmsg_dict_converter/converter.py
rosmsg_dict_converter/demo.py
rosmsg_dict_converter-0.1.2.dist-info/licenses/LICENSE
tests/__init__.py
tests/test_rosmsg_dict_converter.py
rosmsg_dict_converter-0.1.2.dist-info/METADATA
rosmsg_dict_converter-0.1.2.dist-info/WHEEL
rosmsg_dict_converter-0.1.2.dist-info/top_level.txt
rosmsg_dict_converter-0.1.2.dist-info/RECORD
