Metadata-Version: 2.4
Name: rosmsg_dict_converter
Version: 0.1.2
Summary: Provide a  converter to convert ROS message to dict and vice versa
Author: Wing mun Fung
Author-email: fengrongman@gmail.com
Classifier: Programming Language :: Python :: 3
Classifier: License :: OSI Approved :: Apache Software License
Classifier: Operating System :: OS Independent
License-File: LICENSE
Requires-Dist: rich
Requires-Dist: pydantic
Dynamic: author
Dynamic: author-email
Dynamic: classifier
Dynamic: description
Dynamic: description-content-type
Dynamic: license-file
Dynamic: requires-dist
Dynamic: summary
